Workbook

Sheet Dashboard
A1: WEAVING DEPARTMENT | FINANCIAL MANAGEMENT DASHBOARD
A2: Corporate reporting pack • Source data + Pivot Analysis + Pivot Charts • Filter controls
A4: Revenue PKR | D4: Direct Cost PKR | G4: Gross Profit PKR | J4: Margin %
A5: =SUM(Transactions!H5:H34) | D5: =SUM(Transactions!I5:I34) | G5: =SUM(Transactions!J5:J34) | J5: =IFERROR(SUM(Transactions!J5:J34)/SUM(Transactions!H5:H34),0)
A8: INTERACTIVE FILTER PANEL
A9: Month | D9: Account | G9: Department | J9: View
A10: All | D10: All | G10: All | J10: All
A30: Corporate note: Excel-native PivotTable/Slicer objects cannot be authored by openpyxl itself; this workbook includes Excel Tables, formula-driven Pivot Analysis, native dropdown filter controls, and Pivot Charts as a compatible corporate dashboard.

Sheet Transactions
A1: WEAVING DEPARTMENT | FINANCIAL TRANSACTIONS
A2: Illustrative entries; replace sample values with approved company records.
A4: Txn ID | B4: Month | C4: Date | D4: Department | E4: Account | F4: Description | G4: Qty | H4: Revenue (PKR) | I4: Direct Cost (PKR) | J4: Gross Profit (PKR) | K4: Net Cash Flow (PKR)
A5: TXN-0001 | B5: Jan-26 | C5: 46023 | D5: Weaving | E5: Grey Yarn | F5: Sales / production billing | G5: 5392 | H5: 315444 | I5: 318461 | J5: =H5-I5 | K5: =J5
A6: TXN-0002 | B6: Jan-26 | C6: 46028 | D6: Weaving | E6: Weaving Production | F6: Yarn purchase | G6: 1645 | H6: 0 | I6: 409428 | J6: =H6-I6 | K6: =J6
A7: TXN-0003 | B7: Jan-26 | C7: 46033 | D7: Weaving | E7: Job Work | F7: Job-work income | G7: 3401 | H7: 579588 | I7: 309600 | J7: =H7-I7 | K7: =J7
A8: TXN-0004 | B8: Jan-26 | C8: 46038 | D8: Weaving | E8: Utilities | F8: Power expense | G8: 5729 | H8: 0 | I8: 220814 | J8: =H8-I8 | K8: =J8
A9: TXN-0005 | B9: Jan-26 | C9: 46043 | D9: Weaving | E9: Maintenance | F9: Repair expense | G9: 6771 | H9: 0 | I9: 156466 | J9: =H9-I9 | K9: =J9
A10: TXN-0006 | B10: Feb-26 | C10: 46048 | D10: Weaving | E10: Grey Yarn | F10: Sales / production billing | G10: 1375 | H10: 596692 | I10: 239484 | J10: =H10-I10 | K10: =J10
A11: TXN-0007 | B11: Feb-26 | C11: 46053 | D11: Weaving | E11: Weaving Production | F11: Yarn purchase | G11: 7332 | H11: 0 | I11: 271722 | J11: =H11-I11 | K11: =J11
A12: TXN-0008 | B12: Feb-26 | C12: 46058 | D12: Weaving | E12: Job Work | F12: Job-work income | G12: 1653 | H12: 372049 | I12: 172953 | J12: =H12-I12 | K12: =J12
A13: TXN-0009 | B13: Feb-26 | C13: 46063 | D13: Weaving | E13: Utilities | F13: Power expense | G13: 4113 | H13: 0 | I13: 265738 | J13: =H13-I13 | K13: =J13
A14: TXN-0010 | B14: Feb-26 | C14: 46068 | D14: Weaving | E14: Maintenance | F14: Repair expense | G14: 4714 | H14: 0 | I14: 311277 | J14: =H14-I14 | K14: =J14
A15: TXN-0011 | B15: Mar-26 | C15: 46073 | D15: Weaving | E15: Grey Yarn | F15: Sales / production billing | G15: 2332 | H15: 444081 | I15: 306264 | J15: =H15-I15 | K15: =J15
A16: TXN-0012 | B16: Mar-26 | C16: 46078 | D16: Weaving | E16: Weaving Production | F16: Yarn purchase | G16: 2716 | H16: 0 | I16: 259973 | J16: =H16-I16 | K16: =J16
... A34: TXN-0030 | B34: Jun-26 | C34: 46168 | D34: Weaving | E34: Maintenance | F34: Repair expense | G34: 3965 | H34: 0 | I34: 234987 | J34: =H34-I34 | K34: =J34

Sheet Account Summary
A1: WEAVING DEPARTMENT | ACCOUNT SUMMARY
A2: Formula-driven summary using SUMIFS.
A4: Account | B4: Revenue (PKR) | C4: Cost (PKR) | D4: Net (PKR) | E4: Share of Cost | F4: Status
A5: Grey Yarn | B5: =SUMIFS(Transactions!$H$5:$H$34,Transactions!$E$5:$E$34,A5) | C5: =SUMIFS(Transactions!$I$5:$I$34,Transactions!$E$5:$E$34,A5) | D5: =B5-C5 | E5: =IFERROR(C5/SUM($C$5:$C$9),0) | F5: =IF(D5>=0,"Positive","Review")
A6: Weaving Production | B6: =SUMIFS(Transactions!$H$5:$H$34,Transactions!$E$5:$E$34,A6) | C6: =SUMIFS(Transactions!$I$5:$I$34,Transactions!$E$5:$E$34,A6) | D6: =B6-C6 | E6: =IFERROR(C6/SUM($C$5:$C$9),0) | F6: =IF(D6>=0,"Positive","Review")
A7: Job Work | B7: =SUMIFS(Transactions!$H$5:$H$34,Transactions!$E$5:$E$34,A7) | C7: =SUMIFS(Transactions!$I$5:$I$34,Transactions!$E$5:$E$34,A7) | D7: =B7-C7 | E7: =IFERROR(C7/SUM($C$5:$C$9),0) | F7: =IF(D7>=0,"Positive","Review")
A8: Utilities | B8: =SUMIFS(Transactions!$H$5:$H$34,Transactions!$E$5:$E$34,A8) | C8: =SUMIFS(Transactions!$I$5:$I$34,Transactions!$E$5:$E$34,A8) | D8: =B8-C8 | E8: =IFERROR(C8/SUM($C$5:$C$9),0) | F8: =IF(D8>=0,"Positive","Review")
A9: Maintenance | B9: =SUMIFS(Transactions!$H$5:$H$34,Transactions!$E$5:$E$34,A9) | C9: =SUMIFS(Transactions!$I$5:$I$34,Transactions!$E$5:$E$34,A9) | D9: =B9-C9 | E9: =IFERROR(C9/SUM($C$5:$C$9),0) | F9: =IF(D9>=0,"Positive","Review")

Sheet Pivot Analysis
A1: PIVOT ANALYSIS
A2: Management summary tables feeding the dashboard charts.
A3: Account | B3: Revenue PKR | C3: Cost PKR | D3: Gross Profit PKR | E3: Margin %
A4: Grey Yarn | B4: =SUMIFS(Transactions!H:H,Transactions!E:E,A4) | C4: =SUMIFS(Transactions!I:I,Transactions!E:E,A4) | D4: =B4-C4 | E4: =IFERROR(D4/B4,0)
A5: Weaving Production | B5: =SUMIFS(Transactions!H:H,Transactions!E:E,A5) | C5: =SUMIFS(Transactions!I:I,Transactions!E:E,A5) | D5: =B5-C5 | E5: =IFERROR(D5/B5,0)
A6: Job Work | B6: =SUMIFS(Transactions!H:H,Transactions!E:E,A6) | C6: =SUMIFS(Transactions!I:I,Transactions!E:E,A6) | D6: =B6-C6 | E6: =IFERROR(D6/B6,0)
A7: Utilities | B7: =SUMIFS(Transactions!H:H,Transactions!E:E,A7) | C7: =SUMIFS(Transactions!I:I,Transactions!E:E,A7) | D7: =B7-C7 | E7: =IFERROR(D7/B7,0)
A8: Maintenance | B8: =SUMIFS(Transactions!H:H,Transactions!E:E,A8) | C8: =SUMIFS(Transactions!I:I,Transactions!E:E,A8) | D8: =B8-C8 | E8: =IFERROR(D8/B8,0)
